pytest_mirror/__init__.py
pytest_mirror/cli.py
pytest_mirror/constants.py
pytest_mirror/core.py
pytest_mirror/hookspecs.py
pytest_mirror/plugin.py
pytest_mirror/plugin_manager.py
pytest_mirror/py.typed
pytest_mirror/validator.py
pytest_mirror-0.1.1.dist-info/licenses/LICENSE
pytest_mirror-0.1.1.dist-info/METADATA
pytest_mirror-0.1.1.dist-info/WHEEL
pytest_mirror-0.1.1.dist-info/entry_points.txt
pytest_mirror-0.1.1.dist-info/top_level.txt
pytest_mirror-0.1.1.dist-info/RECORD
