Metadata-Version: 2.4
Name: pytest-mirror
Version: 0.1.1
Summary: A pluggy-based pytest plugin and CLI tool for ensuring your test suite mirrors your source code structure
Author: Dan Von Pasecky
Maintainer: Dan Von Pasecky
License: MIT
Project-URL: Homepage, https://github.com/dvonpasecky/pytest-mirror
Project-URL: Repository, https://github.com/dvonpasecky/pytest-mirror.git
Project-URL: Documentation, https://github.com/dvonpasecky/pytest-mirror#readme
Keywords: pytest,testing,test-structure,plugin,cli,mirror,pluggy
Classifier: Development Status :: 4 - Beta
Classifier: Framework :: Pytest
Classifier: Intended Audience :: Developers
Classifier: License :: OSI Approved :: MIT License
Classifier: Operating System :: OS Independent
Classifier: Programming Language :: Python :: 3
Classifier: Programming Language :: Python :: 3.11
Classifier: Programming Language :: Python :: 3.12
Classifier: Programming Language :: Python :: 3.13
Classifier: Topic :: Software Development :: Testing
Classifier: Topic :: Software Development :: Quality Assurance
Classifier: Typing :: Typed
Requires-Python: >=3.11
License-File: LICENSE
Requires-Dist: pluggy>=1.6.0
Dynamic: license-file
